{
  "file_name": "26341645",
  "category": "AUTOMOBILE",
  "name": "SR BUSINESS SYSTEMS ANALYST",
  "email": null,
  "phone": null,
  "skills": [
    "PeopleSoft HCM & Portal",
    "PeopleTools",
    "PeopleSoft Query",
    "SQL",
    "Oracle",
    "Microsoft SQL Server",
    "SharePoint",
    "Windows NT",
    "Windows 2003",
    "Terminal Server",
    "MS Office",
    "Excel",
    "Word",
    "PowerPoint",
    "Project",
    "Publisher",
    "Visio",
    "Access",
    "Rational Tool",
    "SDT",
    "RQM",
    "Clear Case",
    "Document Management Systems",
    "PDM",
    "Documentum",
    "Kronos Workforce Central",
    "Kronos Connect",
    "ADP",
    "Test planning and execution",
    "Project management",
    "Requirements gathering",
    "Strong collaborative skills",
    "Systems development",
    "Document management",
    "Systems implementation",
    "Problem analysis and resolution",
    "Systems integration"
  ],
  "experience": [
    {
      "title": "SR BUSINESS SYSTEMS ANALYST",
      "company": "Company Name",
      "start": "12/2004",
      "end": "Current",
      "description": "Working with several large applications like PeopleSoft(7.5, 8.3 and 8.9 versions), Kronos, ADP PCPW (v.4 and v.5), Nextrak"
    },
    {
      "title": "BUSINESS SYSTEMS ANALYST I/II",
      "company": "Company Name",
      "start": "01/2003",
      "end": "12/2004",
      "description": "Lead BA for the ADP, Kronos and Nextrak applications."
    },
    {
      "title": "HRIS CUSTOMER SERVICE SPECIALIST/ HRIS SPECIALIST",
      "company": "Company Name",
      "start": "01/2001",
      "end": "01/2003",
      "description": null
    }
  ],
  "education": [
    {
      "degree": null,
      "institution": null,
      "year": null
    }
  ],
  "summary": "Motivated and customer-oriented Systems Analyst with strong Analytical and technical skills.",
  "total_years_experience": 23.0,
  "raw_text": "SR BUSINESS SYSTEMS ANALYST\nCareer Overview\nMotivated and customer-oriented Systems Analyst with strong Analytical and technical skills.\nQualifications\nStrong analytical skills Test planning and execution\nProject management Requirements gathering\nStrong collaborative skills Systems development\nDocument management Systems implementation\nProblem analysis and resolution Systems integration\nTechnical Skills\nPeopleSoft HCM & Portal, PeopleTools, PeopleSoft Query\nSQL, Oracle, Microsoft SQL Server\nSharePoint, Windows NT, Windows 2003, Terminal Server\nMS Office - Excel, Word, PowerPoint, Project, Publisher, Visio and Access\nRational Tool (SDT, RQM, Clear Case) , Document Management Systems(PDM & Documentum)\nKronos Workforce Central (WFC), Kronos Connect, ADP\nWork Experience\nSR BUSINESS SYSTEMS ANALYST 12/2004 to Current Company Name City , State\nWorking with several large applications like PeopleSoft(7.5, 8.3 and 8.9 versions), Kronos, ADP PCPW (v.4 and v.5), Nextrak\nWorking with several relational database applications\nProviding Support to specified customer base for HR IS applications in a timely, courteous and professional manner.\nInteracting with interfacing applications for ADP and PeopleSoft\nWorking with business owners to elicit, define and maintain business requirements and transforming them into technical solutions.\nResponsible for developing and execution of test plans to ensure customer requirements are being met.\nFacilitating the resolution of large, complex production system problems by performing initial triage for severity and business impact of\napplication failures.\nActing as a liaison for HRIS application owners/Centers of excellence and Vendor managing these applications.\nResponsible for coordinating and overseeing implementation of various solutions for system change requests and defects in accordance to\nthe vendor change request process.\nPartnered and consulted with HR COEs and BPO to complete the change control process and presented business requirements for\napproval. Also reviewed technical specifications to ensure all requirements submitted were being met.\nEnsuring that SLAs and Quality Compliance across all applicable applications.\nResponsible for identifying and review of downstream impacts across ongoing BSC initiatives.\nSupporting security processes and policies for BSC i.e. data privacy, SOX, Audit etc..\nActing as an Internal Liaison for interfacing applications.\nLeading department small to medium projects in accordance to the guidelines of the Global System Methodology(GSM) standards.\nPrepared and presented project status updates to various stake holder including core team members and project leadership or sponsors.\nCommunicates user requirements to development teams.\nData Analysis and reporting\nHRIS lead for several acquisition project including requirements gathering and integration into core HRIS systems. In addition provided\nsupport to interfacing application to ensure their integration was successful too. Partnered with IS and HR to develop and enhance tools that\nare being leveraged in future acquisitions.\nMentoring/Coaching other Analysts to enhance team performance and ensure success in projects and areas of support.\nBUSINESS SYSTEMS ANALYST I/II 01/2003 to 12/2004 Company Name City , State\nLead BA for the ADP, Kronos and Nextrak applications.\nProvided technical support for several de-centralized ADP Applications and Databases.\nResponsible for Level I and II technical issues\nResponsible for escalation and issue management with the ADP and Payroll Vendors.\nTracked and monitored problems to insure a timely resolution.\nPrepared and maintained documentation pertaining to Systems operation and user documentation.\nIdentifies, researches and resolves areas of improvement by working with the users, operations and development team.\nInvolved in various projects of Application development and events from kickoff to product going live.\nHRIS CUSTOMER SERVICE SPECIALIST/ HRIS SPECIALIST 01/2001 to 01/2003 Company Name City , State\nResponsible for the delivery of technical and functional HR, Payroll and intranet applications support and services to the BSC internal\ncustomers i.e. PeopleSoft, ADP, Webhire, Kronos, etc.\nTracked and monitored problems to the Support Center to insure a timely resolution.\nPrepared and maintained documentation pertaining to Systems operation and user documentation.\nIdentified, researched and resolved areas of improvement by working with the users, operations and development team.\nInvolved in various projects of Application development and events from kickoff to product going live.\nEDI COORDINATOR 09/1999 to 01/2001 Company Name City , State\nEstablished and furthered Trading Partner relationships with customers, third party networks and other business units by working with them\nto implement and expand EDI.\nIdentified and resolved day-to-day system/interface issues which impacted customer satisfaction.\nPerformed EDI Project Management.\nIdentified and implemented process improvement efforts within the EDI structure and customer order management, including system\ninterface and process improvements.\nProvided technical and procedure resources developing new EDI transactions, customer reporting and performance measurements.\nResponsible for the review and analysis of the implementation guides both from Boston Scientific and the customers.\nPrepared documentation to support Trading Partner mapping, implementation and audit purposes.\nResponsible for the research and maintenance of the database structure, common business practices and operational procedures to identify\nareas of potential EDI system incompatibility.\nCUSTOMER SERVICE REPRESENTATIVE 11/1998 to 09/1999 Company Name City , State\nInterfaced with customers, company sales staff, and via telephone and electronic media to process customer orders and handled a variety of\npre-sales or post sales service functions.\nResponded to requests for company product information and refered sales leads to sales staff.\nResolved customer problems and answered inquiries by calling within the organization to related departments.\nResponsible for setting up orders for special product lines for customers and sales groups.\nTrained and coached new hires in the customer service department\nCALL RECEIVER/CUSTOMER SERVICE 01/1998 to 11/1998 Company Name City , State\nHandled emergency road service requests, courteously and completely complying with AAA's Five Diamond Service Standards.\nResolved and handled problem calls using AAA's Five Diamond Advanced Plus Service Standards.\nAssisted members with after hour trip route requests and travel information.\nRecommended additional AAA products and services with increased sales to the southern New England area.\nOperate computer to enter customer inquiries and correct data when needed using Windows 95.\nAssist the supervisor with training new employees in customer service department.\nEducation and Training\nBachelor of Science : Management Information Systems 2000 Northeastern University City , State , USA\nAssociate of Science : Computer Scientific 1998 Quincy College City , State"
}